Ejemplo_Investigacion_P2/calculo.py
Ejemplo_Investigacion_P2/constantes.py
ejemplo_investigacion_p2-0.0.1.dist-info/METADATA
ejemplo_investigacion_p2-0.0.1.dist-info/WHEEL
ejemplo_investigacion_p2-0.0.1.dist-info/licenses/LICENSE
ejemplo_investigacion_p2-0.0.1.dist-info/RECORD
