Metadata-Version: 2.1
Name: Ejemplo_Investigacion_P2
Version: 0.0.1
Summary: Ejemplo de como crear un paquete
Project-URL: Homepage, https://github.com/piedrachin/Proyecto_Inv_Progra2.git
Author-email: piedrachin <stone15@gmail.com>
License: MIT License
License-File: LICENSE
Classifier: License :: OSI Approved :: MIT License
Classifier: Operating System :: OS Independent
Classifier: Programming Language :: Python :: 3
Requires-Python: >=3.11
